blue_south/README.py
blue_south/__init__.py
blue_south/__main__.py
blue_south/content.py
blue_south/host.py
blue_south/logger.py
blue_south/urls.py
blue_south/.abcli/abcli.sh
blue_south/.abcli/actions.sh
blue_south/.abcli/aka.sh
blue_south/.abcli/alias.sh
blue_south/.abcli/blue_south.sh
blue_south/.abcli/browse.sh
blue_south/.abcli/tests/README.sh
blue_south/.abcli/tests/help.sh
blue_south/.abcli/tests/version.sh
blue_south/help/__init__.py
blue_south/help/__main__.py
blue_south/help/functions.py
blue_south-4.24.1.dist-info/licenses/LICENSE
blue_south-4.24.1.dist-info/METADATA
blue_south-4.24.1.dist-info/WHEEL
blue_south-4.24.1.dist-info/top_level.txt
blue_south-4.24.1.dist-info/RECORD
